flask_cacophony/Cacophony.py
flask_cacophony/__init__.py
flask_cacophony/slack.py
Cacophony-0.1.dist-info/METADATA
Cacophony-0.1.dist-info/WHEEL
Cacophony-0.1.dist-info/top_level.txt
Cacophony-0.1.dist-info/RECORD
