Metadata-Version: 2.1
Name: Cacophony
Version: 0.1
Summary: Framework for handling events from Slack/Discord/etc
Home-page: https://gitlab.com/deepy/cacophony
Author: Alex Nordlund
Author-email: deep.alexander@gmail.com
License: BSD
Platform: any
Classifier: Environment :: Web Environment
Classifier: Intended Audience :: Developers
Classifier: License :: OSI Approved :: BSD License
Classifier: Operating System :: OS Independent
Classifier: Programming Language :: Python
Classifier: Topic :: Internet :: WWW/HTTP :: Dynamic Content
Classifier: Topic :: Software Development :: Libraries :: Python Modules
Requires-Dist: Flask
